clapton/__init__.py
clapton/app.py
clapton/base.py
clapton/cli.py
clapton/models.py
clapton/predictions.py
clapton/templates.py
clapton/transforms.py
clapton-0.1.dist-info/METADATA
clapton-0.1.dist-info/RECORD
clapton-0.1.dist-info/WHEEL
clapton-0.1.dist-info/entry_points.txt
clapton-0.1.dist-info/top_level.txt
